DESIGN.md
LICENSE.md
README.md
sping/__init__.py
sping/__main__.py
sping/cli.py
sping/config.py
sping/formatters.py
sping/metrics.py
sping/probe.py
sping/exporters/__init__.py
sping/ui/__init__.py
sping/ui/chart.py
sping/ui/colors.py
sping/util/__init__.py
sping/util/url_helpers.py
service_ping_sping-0.2.11.dist-info/METADATA
service_ping_sping-0.2.11.dist-info/WHEEL
service_ping_sping-0.2.11.dist-info/entry_points.txt
service_ping_sping-0.2.11.dist-info/licenses/LICENSE.md
service_ping_sping-0.2.11.dist-info/RECORD
