Metadata-Version: 2.4
Name: service-ping-sping
Version: 0.2.11
Summary: The sping command provides modern HTTP/TCP latency monitoring with real-time terminal visualization
Project-URL: Homepage, https://dseltzer.gitlab.io/sping/
Project-URL: Repository, https://gitlab.com/dseltzer/sping.git
Project-URL: Issues, https://gitlab.com/dseltzer/sping/-/issues
Project-URL: Changelog, https://gitlab.com/dseltzer/sping/-/releases
Project-URL: Author Profile, https://gitlab.com/dseltzer
Author: dseltzer
Maintainer: dseltzer
License: # MIT License
License-File: LICENSE.md
Keywords: cli,http,httping,latency,monitoring,network,ping,tcp,terminal,tui
Classifier: Development Status :: 4 - Beta
Classifier: Environment :: Console
Classifier: Intended Audience :: Developers
Classifier: Intended Audience :: System Administrators
Classifier: License :: OSI Approved :: MIT License
Classifier: Operating System :: OS Independent
Classifier: Programming Language :: Python :: 3
Classifier: Programming Language :: Python :: 3.9
Classifier: Programming Language :: Python :: 3.10
Classifier: Programming Language :: Python :: 3.11
Classifier: Programming Language :: Python :: 3.12
Classifier: Topic :: Internet :: WWW/HTTP
Classifier: Topic :: System :: Monitoring
Classifier: Topic :: System :: Networking :: Monitoring
Classifier: Topic :: Terminals
Classifier: Topic :: Utilities
Classifier: Typing :: Typed
Requires-Python: >=3.9
Requires-Dist: httpx>=0.27.0
Requires-Dist: rich>=13.0.0
Requires-Dist: typer>=0.9.0
Provides-Extra: dev
Requires-Dist: httpx>=0.27.0; extra == 'dev'
Requires-Dist: pytest-asyncio>=0.21; extra == 'dev'
Requires-Dist: pytest>=7; extra == 'dev'
Provides-Extra: ui
Requires-Dist: textual>=0.58.0; extra == 'ui'
